{
    "version": 1,
    "schedule": {
        "type": "simple",
        "interval": "1s"
    },
    "workflow": {
        "collect": {
            "metrics": {
                "/intel/procfs/processes/*/ps_disk_ops_syscr": {},
                "/intel/procfs/processes/*/ps_disk_ops_syscw": {},
                "/intel/procfs/processes/running": {},
                "/intel/procfs/processes/stopped": {},
                "/intel/procfs/processes/waiting": {}
            },
            "publish": [
                {
                    "plugin_name": "file",
                    "config": {
                        "file": "/tmp/published_processes"
                    }
                }
            ],

            "config": null
        }
    }
}
